noscrape/__init__.py
noscrape/load_noscrape_lib.py
noscrape/noscrape.py
noscrape/bin/noscrape_darwin_arm64
noscrape/bin/noscrape_darwin_x86_64
noscrape/bin/noscrape_linux_aarch64
noscrape/bin/noscrape_linux_x86_64
noscrape/bin/noscrape_windows_x86_64.exe
tests/__init__.py
tests/noscrape_test.py
noscrape-1.0.4.dist-info/METADATA
noscrape-1.0.4.dist-info/WHEEL
noscrape-1.0.4.dist-info/top_level.txt
noscrape-1.0.4.dist-info/RECORD
