Metadata-Version: 2.1
Name: noscrape
Version: 1.0.4
Summary: A package to obfuscate text using Unicode Private Use Area characters
Home-page: https://github.com/noscrape/noscrape-python
Author: Bernhard Schönberger
Author-email: noscrape@gmx.de
Classifier: Programming Language :: Python :: 3
Classifier: Operating System :: OS Independent
Requires-Python: >=3.6
